catboost_extensions/__init__.py
catboost_extensions/feature_selection.py
catboost_extensions/optuna.py
catboost_extensions/utils.py
catboost_extensions-2.8.dist-info/LICENSE
catboost_extensions-2.8.dist-info/METADATA
catboost_extensions-2.8.dist-info/WHEEL
catboost_extensions-2.8.dist-info/top_level.txt
catboost_extensions-2.8.dist-info/RECORD
