Metadata-Version: 2.2
Name: catboost_extensions
Version: 2.8
Summary: Extensions for catboost models
Home-page: https://github.com/dubovikmaster/catboost-extensions
Author: Dubovik Pavel
Author-email: geometryk@gmail.com
Platform: any
Requires-Python: >=3.7
License-File: LICENSE
Requires-Dist: scikit-learn>=1.5
Requires-Dist: tqdm
Requires-Dist: shap
Requires-Dist: catboost
Requires-Dist: optuna
Requires-Dist: parallelbar>=2.5
Dynamic: author
Dynamic: author-email
Dynamic: description
Dynamic: description-content-type
Dynamic: home-page
Dynamic: platform
Dynamic: requires-dist
Dynamic: requires-python
Dynamic: summary
